<!--
Address space for targetting parameters defined in this XML file, e.g.
	/xml/id/
	/xml/mono-circle/output/1/gain

Address space for responding to generic incoming controllers
	/any/other/address

specified inside behaviour <param> tag
-->

<resoundxml 
	xmlns="resound"
	xmlns:xsi="http://www.w3.org/2001/XMLSchema-instance"
	xsi:schemaLocation="http://resound.sourceforge.net resoundnv-schema.xsd"
>


    <!-- Audio stream -->
	<audiostreamfile id="fch1" path="/home/njm79/media/str1.wav" channel="1" gain="1.2"/>
	<audiostreamfile id="fch2" path="/home/njm79/media/str1.wav" channel="2"/>
	<audiostreamfile id="fch3" path="/home/njm79/media/str1.wav" channel="3"/>
	<audiostreamfile id="fch4" path="/home/njm79/media/str1.wav" channel="4"/>
	<audiostreamfile id="fch5" path="/home/njm79/media/str1.wav" channel="5"/>
	<audiostreamfile id="fch6" path="/home/njm79/media/str1.wav" channel="6"/>

	<audiostreamlive id="live1" port="in1"/>		<!-- JACK connections -->
	<audiostreamlive id="live2" port="in2" gain="0.2"/>	

    <!-- Loudspeaker -->
	<loudspeaker id="sp01" port="out1" x="0" y="0" z="0" az="0" el="0" gain="1.0"/>
	<loudspeaker id="sp02" port="out2" x="0" y="0" z="0" az="0" el="0" gain="1.0"/>
	<loudspeaker id="sp03" port="out3" x="0" y="0" z="0" az="0" el="0" gain="1.0"/>
	<loudspeaker id="sp04" port="out4" x="0" y="0" z="0" az="0" el="0" gain="1.0"/>
	<loudspeaker id="sp05" port="out5" x="0" y="0" z="0" az="0" el="0" gain="1.0"/>

<!--
	<loudspeaker id="subs" port="out8" isArray="true" gain="0.3333">	
		<element id="1" x="" y="" z="" az="" el=""/>			
		<element id="2" x="" y="" z="" az="" el=""/>
		<element id="3" x="" y="" z="" az="" el=""/>
	</loudspeaker>
-->
    <!-- CASS -->
	<cass id="5.1-tape-mapping">
		<alias id="L" ref="fch1"/>	<!-- see Audio Stream, above -->
		<alias id="C" ref="fch5" gain="1.1"/>
		<alias id="R" ref="fch2"/>
		<alias id="Ls" ref="fch3"/>
		<alias id="Rs" ref="fch4"/>
		<alias id="LFE" ref="fch6"/>
	</cass>

	<cass id="stereo-mic-pair">
		<alias id="L" ref="live1"/>
		<alias id="R" ref="live2"/>
	</cass>

	<cass id="stereo-tape-mapping">
		<alias id="L" ref="fch1"/>
		<alias id="R" ref="fch2"/>
	</cass>
    <!-- CLS -->
	<cls id="Main5-1">
		<alias id="L" ref="sp01"/>	<!-- alias id is within 'scope' of object -->
		<alias id="C" ref="sp02"/>
		<alias id="R" ref="sp03"/>
		<alias id="Ls" ref="sp04"/>
		<alias id="Rs" ref="sp05"/>
		<alias id="LFE" ref="subs" gain="1.1"/>
	</cls>

	<cls id="Main-Stereo-Front">
		<alias id="L" ref="sp01"/>
		<alias id="R" ref="sp03"/>
	</cls>

	<cls id="Main-Stereo-Rear">
		<alias id="L" ref="sp01"/>
		<alias id="R" ref="sp03"/>
	</cls>

	<cls id="Stereo-East-Pair">
		<alias id="L" ref="sp04"/>
		<alias id="R" ref="sp01"/>
	</cls>


<!--
	<preset id="remap-5-1-tape-mapping">			
		<cass id="5-1-tape-mapping">
			<alias id="L" ref="fch1"/>
			<alias id="C" ref="fch3"/>
			<alias id="R" ref="fch2"/>
			<alias id="Ls" ref="fch5"/>
			<alias id="Rs" ref="fch6"/>
			<alias id="LFE" ref="fch4"/>
		</cass>
	</preset>
-->
    <!-- Behaviour -->
	<behaviour id="behaviour1" class="attenuator">	<!-- One fader, one loudspeaker -->
		<input id="1" ref="stereo-tape-mapping.L"/>
		<output id="2" ref="Main-Stereo-Front.L"/>
		<param id="level" address="/fader/1"/>
	</behaviour>

	<behaviour id="5-1-fader" class="attenuator">	<!-- One fader, 5.1 loudspeakers -->
		<input id="1" ref="5-1-tape-mapping"/>
		<output id="2" ref="Main5-1"/>
		<param id="level" address="/fader/2"/>
	</behaviour>

	<behaviour id="stereo-multi-crossfade" class="multi-crossfade">	<!-- One fader, 5.1 loudspeakers -->
		<input id="1" ref="stereo-mic-pair"/>
		<output id="1" ref="Main-Stereo-Front"/>	<!-- Order of collective == order of XML -->
		<output id="2" ref="Main-Stereo-Rear"/>
		<output id="3" ref="Main-Stereo-Front"/> <!--back to the front pair-->
		<output id="4" ref="Stereo-East-Pair"/>
		<param id="level" address="/fader/3"/>
		<param id="position" address="/fader/4"/>
	</behaviour>

	<behaviour id="mono-circle" class="chase">
		<input id="1" ref="live2"/>
		<output id="1" ref="sp01" gain="0.4" />	<!-- attributes interpreted (or ignored) as appropriate by target behaviour algorithm -->
		<output id="2" ref="sp02"/>
		<output id="3" ref="sp03"/>
		<output id="4" ref="sp04"/>
		<output id="5" ref="sp05"/>
		<param id="amp" address="/joyleft1" value="1.1"/> <!-- value specifies default value-->
		<param id="freq" address="/joyright1" value="1.1"/>
		<param id="phase" value="1.0"/> <!--This one has no osc control assigned and value is threrefore 'locked' at default -->
	</behaviour>
<!--
	<preset id="other-control">
		<behaviour id="mono-circle" class="chase">
			<param id="phase" value="1.0" address="/joyright5"/> 
		</behaviour>
	</preset>
-->
</resoundxml>
